skylab/__init__.py
skylab/__main__.py
skylab/api.py
skylab/css/styles.css
skylab/models/__init__.py
skylab/models/event_models.py
skylab/models/launch_models.py
skylab/settings.py
skylab/skylab.py
skylab/widgets/__init__.py
skylab/widgets/event_widget.py
skylab/widgets/launch_widget.py
skylab/widgets/time_widget.py
skylab-0.2.1.dist-info/entry_points.txt
skylab-0.2.1.dist-info/LICENSE
skylab-0.2.1.dist-info/METADATA
skylab-0.2.1.dist-info/WHEEL
skylab-0.2.1.dist-info/RECORD
